anp/__init__.py
anp/anp_crawler/API_IMPROVEMENTS.md
anp/anp_crawler/API_PROPOSAL.md
anp/anp_crawler/Interface.md
anp/anp_crawler/README.cn.md
anp/anp_crawler/README.md
anp/anp_crawler/__init__.py
anp/anp_crawler/anp_client.py
anp/anp_crawler/anp_crawler.py
anp/anp_crawler/anp_interface.py
anp/anp_crawler/anp_parser.py
anp/anp_crawler/test/README.md
anp/anp_crawler/test/__init__.py
anp/anp_crawler/test/example_embedded_openrpc.py
anp/anp_crawler/test/run_tests.py
anp/anp_crawler/test/test_anp_crawler.py
anp/anp_crawler/test/test_data_agent_description.json
anp/anp_crawler/test/test_data_embedded_openrpc.json
anp/anp_crawler/test/test_data_openrpc.json
anp/ap2/README.md
anp/ap2/__init__.py
anp/ap2/cart_mandate.py
anp/ap2/credential_mandate.py
anp/ap2/mandate.py
anp/ap2/models.py
anp/ap2/payment_mandate.py
anp/authentication/__init__.py
anp/authentication/did_wba.py
anp/authentication/did_wba_authenticator.py
anp/authentication/did_wba_verifier.py
anp/authentication/verification_methods.py
anp/e2e_encryption/__init__.py
anp/e2e_encryption/message_generation.py
anp/e2e_encryption/short_term_key_generater.py
anp/e2e_encryption/wss_message_client.py
anp/e2e_encryption/wss_message_sdk.py
anp/fastanp/AUTH_UPDATE_SUMMARY.md
anp/fastanp/CONTEXT_UPDATES.md
anp/fastanp/IMPLEMENTATION.md
anp/fastanp/QUICKSTART.md
anp/fastanp/README.md
anp/fastanp/TEST_REPORT.md
anp/fastanp/__init__.py
anp/fastanp/ad_generator.py
anp/fastanp/context.py
anp/fastanp/fastanp.py
anp/fastanp/information.py
anp/fastanp/interface_manager.py
anp/fastanp/middleware.py
anp/fastanp/models.py
anp/fastanp/test_agent_domain_normalization.py
anp/fastanp/utils.py
anp/meta_protocol/__init__.py
anp/meta_protocol/meta_protocol.py
anp/meta_protocol/protocol_negotiator.py
anp/meta_protocol/code_generator/__init__.py
anp/meta_protocol/code_generator/code_generator.py
anp/meta_protocol/code_generator/provider_generator.py
anp/meta_protocol/code_generator/requester_generator.py
anp/node/DESIGN.cn.md
anp/node/DESIGN.md
openanp-0.1.0.dist-info/METADATA
openanp-0.1.0.dist-info/WHEEL
openanp-0.1.0.dist-info/licenses/LICENSE
openanp-0.1.0.dist-info/RECORD
