Metadata-Version: 2.4
Name: openanp
Version: 0.1.0
Summary: An SDK that enables agents to connect with each other, allowing them to perform identity authentication, end-to-end encrypted communication, automatic protocol negotiation based on LLMs, and efficient data exchange.
Project-URL: Homepage, https://agent-network-protocol.com/
Project-URL: Repository, https://github.com/agent-network-protocol/AgentConnect
Project-URL: Documentation, https://github.com/agent-network-protocol/AgentNetworkProtocol
Author-email: changshan <chgaowei@gmail.com>
License: MIT
License-File: LICENSE
Keywords: agent,authentication,communication,encryption,protocol
Classifier: License :: OSI Approved :: MIT License
Classifier: Operating System :: OS Independent
Classifier: Programming Language :: Python :: 3
Requires-Python: >=3.8
Requires-Dist: aiohttp>=3.10.10
Requires-Dist: asn1crypto>=1.5.1
Requires-Dist: base58>=2.1.1
Requires-Dist: canonicaljson>=2.0.0
Requires-Dist: cryptography>=43.0.3
Requires-Dist: ecdsa>=0.19.0
Requires-Dist: jcs>=0.2.1
Requires-Dist: jsonschema>=4.23.0
Requires-Dist: pydantic<3.0.0,>=2.9.2
Requires-Dist: pyjwt>=2.9.0
Requires-Dist: python-dotenv>=1.0.1
Requires-Dist: requests>=2.32.3
Requires-Dist: websockets>=13.1
Provides-Extra: api
Requires-Dist: fastapi<1.0.0,>=0.115.4; extra == 'api'
Requires-Dist: openai>=1.54.3; extra == 'api'
Requires-Dist: uvicorn<1.0.0,>=0.32.0; extra == 'api'
Provides-Extra: dev
Requires-Dist: pytest-asyncio>=0.23.0; extra == 'dev'
Requires-Dist: pytest>=8.0.0; extra == 'dev'
